{"__version": 1, "token_id": 687995, "symbol": "OBJKT", "name": "Cosmidelica #4", "description": "Cosmidelica is a 1/1 collection of the exploration of the internal, external, and eternal.\n \nA blend of the cosmic, the psychedelic, and the spiritual, cosmidelica aims to highlight the connection between the things within us and the things around us.\n \nUt supra sic infra, ut intus sic extra.", "artifact_uri": "ipfs://QmeN2Aq7LiLHqq4oZk1CDeMBTJkvMPh3F1kosAkt4qKnVS", "display_uri": "ipfs://QmTKkbyBP47AmVTE579bafevAzfaASrp1y2zN7AgXhfi7F", "thumbnail_uri": "ipfs://QmanSJJBJiT1GAG5btZSaTJLtqioMaxYoYHp2Gfb7EfzkH", "formats": [{"uri": "ipfs://QmeN2Aq7LiLHqq4oZk1CDeMBTJkvMPh3F1kosAkt4qKnVS", "mimeType": "image/png"}], "creators": ["tz1QQdKKXHLXidNcqZNVXqWhcz4dNK4cfyLd"], "tags": [], "extra": {}}