{"__version": 1, "token_id": 642707, "symbol": "OBJKT", "name": "\u00af\\_(\u30c4)_/\u00af", "description": "hope you have fun watching this\nmade in c4d \n\n13 seconds looped video without sound. \n1280 x 1280 \n30 fps \n.h264", "artifact_uri": "ipfs://QmWNkSgsSrKfdSutxinG73Hyw8ymxRVWDnzTYmNF6kpTM2", "display_uri": "ipfs://QmXGNmHBJMYZN9W9HEhmtcf9tMJttqFcPiBYTTCEYt1m1U", "thumbnail_uri": "ipfs://QmNrhZHUaEqxhyLfqoq1mtHSipkWHeT31LNHb1QEbDHgnc", "formats": [{"uri": "ipfs://QmWNkSgsSrKfdSutxinG73Hyw8ymxRVWDnzTYmNF6kpTM2", "mimeType": "video/mp4"}], "creators": ["tz1QqqsrEw2Hkd6v7FicMp13tzMxa4YMusMR"], "tags": ["90s", "render", "aesthetics", "c4d", "wtf", "shitpost", "ok", "", "videoloop", "loop", ".h264aesthetics3d", "tvshows", "hicetnunc2000", "meme", "motionmeme"], "extra": {}}