{"__version": 1, "token_id": 662054, "symbol": "OBJKT", "name": "brown the olivia", "description": "All elements can confirm his presence. They called her mother of earth!\n\ncollection name (Inside And Outside woman )\n\nThese lines come from the time that I was full of imagination.\nI used these lines to arrive at the concept of women\u2019s inner complexity.\nWomen are beautiful and calm from the outside\nBut from the inside they are full of spiritual conflicts for their evolution\nBeing a woman is one of the most difficult challenges in the world\n", "artifact_uri": "ipfs://QmTKb2TC91StdMGFx5BAAVcvNbw4WQ3auL3EhcG79As8eh", "display_uri": "ipfs://QmQtFdDrY9cPhWmCTjUTzswDYPAUyJVW1jx8hNr2ndjxDf", "thumbnail_uri": "ipfs://QmNrhZHUaEqxhyLfqoq1mtHSipkWHeT31LNHb1QEbDHgnc", "formats": [{"uri": "ipfs://QmTKb2TC91StdMGFx5BAAVcvNbw4WQ3auL3EhcG79As8eh", "mimeType": "image/png"}], "creators": ["tz1dP7P6UBmcE8WBFbRsvsLGpWkiJkU2VmiB"], "tags": ["digitalart", "insideandoutside", "digitalpainting", "cleannft", "woman"], "extra": {}}