{"__version": 1, "token_id": 696254, "symbol": "OBJKT", "name": "NFT #4554", "description": "", "artifact_uri": "ipfs://QmVs6nDLZ4k95uo68HE4ueC9WrbHFxNU6dTcrsYLz3BJGe", "display_uri": "ipfs://QmdTezomawx9KDA7FYBiCqArqfXwrmmT2Zpc89ncymswr9", "thumbnail_uri": "ipfs://QmNrhZHUaEqxhyLfqoq1mtHSipkWHeT31LNHb1QEbDHgnc", "formats": [{"uri": "ipfs://QmVs6nDLZ4k95uo68HE4ueC9WrbHFxNU6dTcrsYLz3BJGe", "mimeType": "video/mp4"}], "creators": ["tz1N4Ufn5i8DAotLqQ2hCi4HtjwSd1EM2mDp"], "tags": ["nft", "lnftart", "nftartist", "nftcollector", "nftcommunity", "nftdrop", "nftcollection", "scalesofsociety", "artistsoninstagram", "digitalart", "illustration", "dragon", "digitalartist", "dragonart", "robodragon", "nftartgallery", "crypto", "cryptoartist", "cryptocollectibles", "cryptoavatar", "eth", "ethereum", "cryptoartwork", "rarenft", "opensea", "ethereum", "fantasy", "lcryptocommunity", "metaverse", "seeingred", "womanhero", "hero", "goddess", "king", "mexicanhero", "mexicana", "bruja", "aztec", "detroit"], "extra": {}}