{"__version": 1, "token_id": 648376, "symbol": "OBJKT", "name": "NEBUXEL - COMPUTING", "description": "Fourth protagonist of the Nebuxel series, we present to you \u201ccomputing\u201d.\n \nThis subject, \u201ccomputing\u201d, represents the computing power that constantly supports and drives the metaverse. As a matter of fact, the latter already embodies an ultimate degree of power both within the economic and geopolitical fields but not only: in the short term, also Medicine and Diagnostics will also follow, strongly relying on this computational power.\n \nSo you can really say that whoever possesses more computing power in a certain sense has the upper hand and follows \"computa et impera\" as a general rule.\n", "artifact_uri": "ipfs://Qma8zXJLFEbKpnrnUhztKSWm4i8tdww1t2BL9UC3ko78ot", "display_uri": "ipfs://QmV27vr75siMa95fxtWauo7q8DQD8VHz13zsyP1MAYHvhT", "thumbnail_uri": "ipfs://QmNrhZHUaEqxhyLfqoq1mtHSipkWHeT31LNHb1QEbDHgnc", "formats": [{"uri": "ipfs://Qma8zXJLFEbKpnrnUhztKSWm4i8tdww1t2BL9UC3ko78ot", "mimeType": "video/quicktime"}], "creators": ["tz2F56onbyxZ2MypDhZ8dmksUjiz8nFGuH28"], "tags": ["nebuxel004", "nebuxel", "004", "gammatrace", "computing"], "extra": {}}