{"__version": 1, "token_id": 672773, "symbol": "OBJKT", "name": "Feeling All of It", "description": "This is the last of 4 paintings for 2021 that I wanted to share with my NFT family and friends.  This was made on a day of great sorrow, a day I can still feel from time to time.  But even then there was some hope in the darkness.  \n\nAcrylic on canvas.", "artifact_uri": "ipfs://QmdKa4oFLtQCQasUCdUqVB9LzsQvxr9yQGdCWErjqmfWYY", "display_uri": "ipfs://QmczRtwv93XyPWSZQwz74nbgpCuTDecqX3R2AvYUeFPU1y", "thumbnail_uri": "ipfs://QmNrhZHUaEqxhyLfqoq1mtHSipkWHeT31LNHb1QEbDHgnc", "formats": [{"uri": "ipfs://QmdKa4oFLtQCQasUCdUqVB9LzsQvxr9yQGdCWErjqmfWYY", "mimeType": "image/png"}], "creators": ["tz1ZfApCB1rmfyByn9e1jj1w9jLSY1wfu9dm"], "tags": ["paint", "painting", "canvas", "sad", "feeling", "feel", "feelings"], "extra": {}}