{"__version": 1, "token_id": 661331, "symbol": "OBJKT", "name": "CRYM34R1V3R", "description": "\u2524cry me a river \u251c\n#1 Genesis by Lennon_cmyk\n\n\nI can't be bought, you have to earn me, apply for an edition...\n\n--> Write to me. On Twitter @lennon_cmyk . Then I come to you, directly into your wallet. So maybe, because I am for friends and acquaintances, fans and nice people only. Just send me your Tezos wallet.\n\nhttps://linktr.ee/lennon_cmyk\n\n(February 2022)", "artifact_uri": "ipfs://Qmc3C42FHVsLeXwHLSkckSkCUURC82To3BCrBDgsbpNetT", "display_uri": "ipfs://Qmc3C42FHVsLeXwHLSkckSkCUURC82To3BCrBDgsbpNetT", "thumbnail_uri": "ipfs://QmNrhZHUaEqxhyLfqoq1mtHSipkWHeT31LNHb1QEbDHgnc", "formats": [{"uri": "ipfs://Qmc3C42FHVsLeXwHLSkckSkCUURC82To3BCrBDgsbpNetT", "mimeType": "image/gif"}], "creators": ["tz1MeaaLXsmfVfRM3LjvTRCwPxsCy3Wiy1FL"], "tags": ["portrait", "lennon", "cmyk", "genesis", "#1", "rainbow", "polychrome", ".gif", "1500x2000px", "wallpaper", "background", "February2022", ""], "extra": {}}