{"__version": 1, "token_id": 701231, "symbol": "OBJKT", "name": "Natey A02", "description": "sound is the purest form of the energy\nwe tune ourselves with the universe\nWe make the Real Unique Handmade Clay Flute Sculptures with magical frequencies, Make the Images of them, recording the sound of the Flute and make them as an ", "artifact_uri": "ipfs://QmavAY5eCgHEMLnB8LzRBArjBksnwPsPHWQaatC3Vx3JEo", "display_uri": "ipfs://QmQtW4vQ2qgvcGLhpXbWkwCmzYXuHb73TE39UUbKdkcD95", "thumbnail_uri": "ipfs://QmNrhZHUaEqxhyLfqoq1mtHSipkWHeT31LNHb1QEbDHgnc", "formats": [{"uri": "ipfs://QmavAY5eCgHEMLnB8LzRBArjBksnwPsPHWQaatC3Vx3JEo", "mimeType": "video/mp4"}], "creators": ["tz1aFMdoUW54QucDbCPhK8SvJXBzYYx2L9Re"], "tags": ["sound", "music", "healing", "shamanic", "nativeamerican", "nft"], "extra": {}}