{"__version": 1, "token_id": 674552, "symbol": "OBJKT", "name": "Walk on the Wild Side", "description": "I said, \"Hey, Joe. Take a walk on the wild side\"\n\nAnalog video art.\nWJ-AVE55 +  Mx1 + Edirol v-4 /  Recorded with capture card and digitally post-processed.\n\nelbi - 2022", "artifact_uri": "ipfs://QmNwXT8S3yB2YuMCugQcWm9GnBjMhfTTnTUQZPrd7n4Bbp", "display_uri": "ipfs://QmNwXT8S3yB2YuMCugQcWm9GnBjMhfTTnTUQZPrd7n4Bbp", "thumbnail_uri": "ipfs://QmNrhZHUaEqxhyLfqoq1mtHSipkWHeT31LNHb1QEbDHgnc", "formats": [{"uri": "ipfs://QmNwXT8S3yB2YuMCugQcWm9GnBjMhfTTnTUQZPrd7n4Bbp", "mimeType": "image/gif"}], "creators": ["tz1TXG3VHtdsSc95Y4HFHBk43hR8MW8f3jYa"], "tags": ["analog", "video", "gif", "videoart", "glitch", "glitchart", "videofeedback"], "extra": {}}