{"__version": 1, "token_id": 642766, "symbol": "OBJKT", "name": "Peacock", "description": "Peacock Dance (Tari Merak) is a tradisional dance from west java, was created around 1950s. One of traditional dance that express animal life.The movement is taken from the life of a peacock.\n\nThis is 1 of 3 works that i will make for the West Java traditional dance series.", "artifact_uri": "ipfs://QmZVeyAgEvS8FzP8vXEZxTvCqDsSFJRvnkouBu9eR5MY2q", "display_uri": "ipfs://Qmd9iun5fDbAcP4DqK9EjDNHBZ9A1i5tYPjsXrzcMLx1Vn", "thumbnail_uri": "ipfs://QmNrhZHUaEqxhyLfqoq1mtHSipkWHeT31LNHb1QEbDHgnc", "formats": [{"uri": "ipfs://QmZVeyAgEvS8FzP8vXEZxTvCqDsSFJRvnkouBu9eR5MY2q", "mimeType": "image/jpeg"}], "creators": ["tz1SZQteDkqfEdJkWHDU1YLtV5o9HmWQca7j"], "tags": ["traditionalart", "illustration", "digitalartwork", "kiwski"], "extra": {}}