{"__version": 1, "token_id": 667455, "symbol": "OBJKT", "name": "Chinese zodiac series (goat) ", "description": "People with the Goat zodiac sign were born in 1943, 1955, 1967, 1979, 1991, 2003, 2015 and 2027.\nIn the Chinese zodiac, the goat has positive, creative, and imaginative energy. In addition, the figure of the goat zodiac is also full of affection and courtesy.\n", "artifact_uri": "ipfs://QmZvGTdEJ6yBVF67iSgmUA7nnsVV61p8jZgYUrYzVrLZNT", "display_uri": "ipfs://QmQ66gMawz7YpQHdmK4Qs1Wm3dSQqGPTVAvSeQt3GmMjAA", "thumbnail_uri": "ipfs://QmNrhZHUaEqxhyLfqoq1mtHSipkWHeT31LNHb1QEbDHgnc", "formats": [{"uri": "ipfs://QmZvGTdEJ6yBVF67iSgmUA7nnsVV61p8jZgYUrYzVrLZNT", "mimeType": "image/png"}], "creators": ["tz2GHphT61PgUmUss7pbUSPr1SqAi6Ha2bd6"], "tags": ["Shio", "goat", "Chinese", "zodiac", "pixel", "pixelart", "cute", "doodle"], "extra": {}}