{"__version": 1, "token_id": 661148, "symbol": "OBJKT", "name": "Please Stand By -I Got Something To Say 130", "description": "Please Stand By utilizes the iconic SMPTE color bars template and changes the palette to bring into question viewers perceptions surrounding \"standards of color.\" An offshoot of my original series, I Got Something To Say, adds an additional more literal message. Please Stand By, Solving The Wordle. The puzzle craze has taken over the world in 2022, but enjoy it while you can because after being bought out by the NY Times it will almost definitely be behind a paywall in the not so distant future.", "artifact_uri": "ipfs://QmYgXDnRLCobcg5e5jnjoFFDkTfpBDDakuM8s7LeNtQFFa", "display_uri": "ipfs://QmdmiDrhqvTwMFoAvftokjH1Mnc3HbnBq9coj4usiiU2Zq", "thumbnail_uri": "ipfs://QmNrhZHUaEqxhyLfqoq1mtHSipkWHeT31LNHb1QEbDHgnc", "formats": [{"uri": "ipfs://QmYgXDnRLCobcg5e5jnjoFFDkTfpBDDakuM8s7LeNtQFFa", "mimeType": "video/mp4"}], "creators": ["tz1VCtzuZHriPNays8UJnAdrZDgRaPehud2Y"], "tags": ["art", "digitalart", "glitch", "glitchart", "color", "colorpalette", "colorpalettes", "tv", "television"], "extra": {}}