{"__version": 1, "token_id": 542213, "symbol": "OBJKT", "name": ".21 FUTURE NFT DISPLAY TOMBSTONE *SOUND ON*. Lucky Lucy van Delft", "description": "basically these kind of things can not be left to their own devices. upon death hopefully the whole NFT archive will be in legacy mode already to benefit other artists after I die (one day). so far haven't figured out how to do that but this is a great start! just to be safe i already sent a version of the this to a tombstone maker so they can start thinking about it in advance. (and mainly to take credit for this original idea before they think of it.)\n\nyear created - 2021\n\n\n\nhttps://soundbible.com/882-Heart-Rate-Monitor-Flatline.html#\nshout out for the sound clip!\n\ncreative commons license\n\nlove,\nlucy\nxxoo\n\n\"i did my best, gave a shit and found a gun in vermeer's view of delft.\"\n\n(p.s. will also mint this exact same thing in opensea just because it's really important, but it wont be for sale.)", "artifact_uri": "ipfs://QmNen3Jb55diGntizU6t7neSxi4nRkoqDUifMcf4bBYuHi", "display_uri": "ipfs://QmcgceZvPPQE9WTrrn7qyBFWushg4mzVVQeCctMcfpXMRi", "thumbnail_uri": "ipfs://QmNrhZHUaEqxhyLfqoq1mtHSipkWHeT31LNHb1QEbDHgnc", "formats": [{"uri": "ipfs://QmNen3Jb55diGntizU6t7neSxi4nRkoqDUifMcf4bBYuHi", "mimeType": "video/mp4"}], "creators": ["tz1fziiZdiG4myWUoBNg4YqyFikWXs7WUjxE"], "tags": ["dead", "death", "goner", "expired", "extinct", "bye-bye", "legacy", "legacyplanning", "nftdisplay", "tombstone", "headstone", "morbid", "dark", "cheeky", "lucy", "llvd", "delft", "luckylucy", "#supportartists"], "extra": {}}