{"__version": 1, "token_id": 502916, "symbol": "OBJKT", "name": "Accidentes 08", "description": "@cdlcpics_NFT\na series of phptographs that came as result of a broken lens.\ni enjoyed the movement and colour on them.", "artifact_uri": "ipfs://QmWGRTVnQrPb5kNuQH4AFFUZTJCSwoKDwKfWYDFhoZkruK", "display_uri": "ipfs://QmTD8C1Sg9toq7Y2fuonG3AtaQnDuhmJQhv5Yi3XcxbVR8", "thumbnail_uri": "ipfs://QmNrhZHUaEqxhyLfqoq1mtHSipkWHeT31LNHb1QEbDHgnc", "formats": [{"uri": "ipfs://QmWGRTVnQrPb5kNuQH4AFFUZTJCSwoKDwKfWYDFhoZkruK", "mimeType": "image/jpeg"}], "creators": ["tz1UZnN4cuBF8cYqmerPDHQpcDGHAvUCE9wT"], "tags": ["abstractphotography", "photography", "colours", "fotograf\u00edaabstracta", "abstract", "abstracto", "fotograf\u00edaglitchglitchphotography"], "extra": {}}