{"__version": 1, "token_id": 686789, "symbol": "OBJKT", "name": "The Psychonaut Smoothie", "description": "The Psychonaut Smoothie consist of 5 grams of Psilocybe Cubensis and 0.5 liters of fresh squeezed orange juice. We recommend taking this on an empty stomach, after a full night's sleep. This drink is sacred to our staff and should be given the respect it deserves. Limit one drink per customer. ", "artifact_uri": "ipfs://QmTAfBG2WTMJVqqLxM9rg7YETLXjqjCYERL2uJcYCkSSK6", "display_uri": "ipfs://QmbH4Z2jJMWmsBCDu9gDT7X8c5VjxN8bSQSRBYMXZwssGH", "thumbnail_uri": "ipfs://QmNrhZHUaEqxhyLfqoq1mtHSipkWHeT31LNHb1QEbDHgnc", "formats": [{"uri": "ipfs://QmTAfBG2WTMJVqqLxM9rg7YETLXjqjCYERL2uJcYCkSSK6", "mimeType": "image/jpeg"}], "creators": ["tz1UcvTAi62FgF6PDsmkGfVCHgc7VFeFGi6V"], "tags": ["GAN"], "extra": {}}