{"__version": 1, "token_id": 650349, "symbol": "OBJKT", "name": "body #84", "description": "this is what you look like when you look inside yourself\n\na part of body-spirit-soul series. amalgamation: poxagronka x ddf35.\ninspired by physicality, technical distortions and awry tools usage, solitude, v60, relocation\n", "artifact_uri": "ipfs://QmXWmv55VJbKsdozL9yBidF9ihwCaKkpaQ2evC34eauQ8V", "display_uri": "ipfs://QmcGw46r3Pcqf6WqzMcsZSRKJ6Ajg67dcjhhEzFfo999p2", "thumbnail_uri": "ipfs://QmNrhZHUaEqxhyLfqoq1mtHSipkWHeT31LNHb1QEbDHgnc", "formats": [{"uri": "ipfs://QmXWmv55VJbKsdozL9yBidF9ihwCaKkpaQ2evC34eauQ8V", "mimeType": "image/jpeg"}], "creators": ["tz2CTX9f1man34Ut5axK7hBAexHJEdT3QYWm"], "tags": ["naked", "photography", "poxagronka", "ddf35", "glitchart", "avatar", "spirit", "abstract", "experimental"], "extra": {}}