{"__version": 1, "token_id": 683449, "symbol": "OBJKT", "name": "Einherjer", "description": "Imagine arriving tired from sailing and being a little seasick from the crazy tide and after several hours you find this relaxing and magical bar to hang out  \n\nPass the fights start after the ATP schedule....", "artifact_uri": "ipfs://QmcxwcqEPszeE8Mj9FQportcQ4tYsKbax2dUJ47qVDbqy3", "display_uri": "ipfs://QmcxwcqEPszeE8Mj9FQportcQ4tYsKbax2dUJ47qVDbqy3", "thumbnail_uri": "ipfs://QmNrhZHUaEqxhyLfqoq1mtHSipkWHeT31LNHb1QEbDHgnc", "formats": [{"uri": "ipfs://QmcxwcqEPszeE8Mj9FQportcQ4tYsKbax2dUJ47qVDbqy3", "mimeType": "image/gif"}], "creators": ["tz1WrCjBV5htFcfSufNiSFsXouENTVb22g4s"], "tags": ["vikings", "vikingos", "rol", "room", "navegar", "maps", "pixel", "bar"], "extra": {}}