{"__version": 1, "token_id": 672937, "symbol": "OBJKT", "name": "072 Flip it", "description": "\u039b\uff4e\u2591\uff49\uff44\uff45\uff41\u2591\uff54\uff4f\u2591\uff41\uff4e\u2591\uff49\uff44\uff45\uff41\u2591\uff46\uff52\uff4f\uff4d\u2591\uff41\uff4e\u2591\uff49\uff44\uff45\uff41\u2591\uff54\uff4f\u2591\uff41\uff4e\uff4f\uff54\uff48\uff45\uff52\u2591\uff49\uff44\uff45\uff41\u2591\uff49\uff44\uff45\uff41\u2591\uff49\uff44\uff45\uff41\uff0e\uff0e\uff0e\u2591\uff4c\uff45\uff54\uff07\uff53\u2591\uff46\uff4c\uff49\uff50\u2591\uff49\uff54\u3000\uff08\u30ab\u8b01\u30d1\u4f55\u3000 \u305f\u3000\u30b8\u309a\u304f\u6848\u30f3\u5bb4\u306d\u30d4\u5104\u6bb4\uff09\n\n\u00b0\u00a4*(\u00af\u00b4\u2605`\u00af)*\u00a4\u00b0\u2022\n\nA \uff4d \uff42\uff45\uff52\uff53\u2591\uff4f\uff46\u2591\uff54\uff48\uff45\u2591\uff32\uff45\uff41\uff4c\uff54\uff49\uff4d\uff45 \u301052-80\u3011 \ud835\ude1a\ud835\ude16\ud835\ude14\ud835\ude09\ud835\ude19\ud835\ude0c \ud835\ude1a\ud835\ude16\ud835\ude10\ud835\ude19\ud835\ude0c\ud835\ude0c \ud835\ude34\ud835\ude26\ud835\ude33\ud835\ude2a\ud835\ude26\ud835\ude34\n\n\u00a4\u00b8\u00b8.\u2022\u00b4\u00af`\u2022\u00b8\u00b8.\u2022.\u00b8\u00b8.\u2022\u00b4\u00af`\u2022\u00b8\u00b8.\u2022.\u00b8\u00b8.\u2022\u00b4\u00af`\u2022\u00b8\u00b8.\u2022.\u00b8\u00b8.\u2022\u00b4\u00af`\u2022\u00b8\u00b8.\u2022.\u00b8\u00b8.\u2022\u00b4\u00af`\nI can produce high Res long length output of this kind of visuals, if you're interested DM me.", "artifact_uri": "ipfs://QmYR9mDmSHzh3Qu2pfmc8vWzLKdmZbG8Nj8sH325JJ87Bw", "display_uri": "ipfs://QmbdtCJHcK5tk3h9PdHsKkxJ5TcFxW4xH74DZ2oaeoVEAP", "thumbnail_uri": "ipfs://QmNrhZHUaEqxhyLfqoq1mtHSipkWHeT31LNHb1QEbDHgnc", "formats": [{"uri": "ipfs://QmYR9mDmSHzh3Qu2pfmc8vWzLKdmZbG8Nj8sH325JJ87Bw", "mimeType": "video/mp4"}], "creators": ["tz1QFyjHEp3kfeyEuMAAcuc4oYZjmrMjn9vx"], "tags": ["Generativeart", "ASCII", "Realtime", "Aotr", "Ambersoftherealtime", "Touchdesigner", "3d", "art", "glitchart", "newmediaart", "reuse", "f_lse_no", "realtimemotiongraphics", "VJART", "VJ"], "extra": {}}