{"__version": 1, "token_id": 655717, "symbol": "OBJKT", "name": "Fried", "description": "Abstract Digital Art by Tankuss", "artifact_uri": "ipfs://QmZkmVC2mbUo4pQrChBdcVL9dvqkgiNXWyCdM9EDWK5ZwJ", "display_uri": "ipfs://QmdW28kFHVfk2cTDkaFpk1GNZJNXHsVyJVqCGG1v58WrKk", "thumbnail_uri": "ipfs://QmNrhZHUaEqxhyLfqoq1mtHSipkWHeT31LNHb1QEbDHgnc", "formats": [{"uri": "ipfs://QmZkmVC2mbUo4pQrChBdcVL9dvqkgiNXWyCdM9EDWK5ZwJ", "mimeType": "image/jpeg"}], "creators": ["tz1XFaWYtwrrjZcs49qDsF6hyn2jfshcoqhF"], "tags": ["abstract", "art", "abstractart", "artist", "painting", "contemporaryart", "artwork", "abstractpainting", "modernart", "artistsoninstagram", "design", "artoftheday", "drawing", "photography", "instaart", "digitalart", "artgallery", "fineart", "acrylicpainting", "abstractartist", "arte", "abstractexpressionism", "illustration", "abstraction", "gallery", "creative", "artcollector", "paint", "acrylic", "bhfyp"], "extra": {}}