{"__version": 1, "token_id": 643112, "symbol": "OBJKT", "name": "Kitsune red (edit)", "description": "Painting of Kitsune (Japanese fox). In Japanese folklore, these animals have great knowledge, long life, and magical powers. Chief among them is the ability to take the form of a person.\n\nPainiting made by acrilics colors. Handmade painting with digital edit.\n", "artifact_uri": "ipfs://QmSTb1mcmq83TCPbscjouKnJjeh3n32jEbhKtwFC799gSy", "display_uri": "ipfs://QmSVsC81tyM5yteFwHrEj2Khvai1YK7hHGidBGetydWUwr", "thumbnail_uri": "ipfs://QmNrhZHUaEqxhyLfqoq1mtHSipkWHeT31LNHb1QEbDHgnc", "formats": [{"uri": "ipfs://QmSTb1mcmq83TCPbscjouKnJjeh3n32jEbhKtwFC799gSy", "mimeType": "image/jpeg"}], "creators": ["tz1V1rBFHGyitCpjwjzNJBmDqoQHQuQaxmRZ"], "tags": ["Kitsune", "Japan", "Japanesefox", "handmade", "acrylic", "folklore", "animal", "fox", "paining"], "extra": {}}