{"__version": 1, "token_id": 654712, "symbol": "OBJKT", "name": "Portrait of Pembroke Welsh Corgi Named Dumbo", "description": "Dumbo just turned 1 year old November 2021.\n\nHe is very smart, understand commands from us such as, sit, stay, hand, up, and etc.\n\nDumbo likes to people rub his belly.\n\nEverytime I meet Dumbo, he always asked me to rub his belly.\n\nHe will come to me, he will give his head first to my hand, and then he lay to me.\n\nAnd then he will enjoy his belly being rubbed by me.\n\nI am looking forward to make Dumbo famous.\n\nLet's make him a celebdog!", "artifact_uri": "ipfs://QmX5Z3R1yp8RR69PNNiGxkWjG829ehzEDHy7ueeqNQfeGs", "display_uri": "ipfs://QmRQkPmFTBAryKJGowKxQKZZj8GPSvHDfPQTDi7rmy9FS8", "thumbnail_uri": "ipfs://QmNrhZHUaEqxhyLfqoq1mtHSipkWHeT31LNHb1QEbDHgnc", "formats": [{"uri": "ipfs://QmX5Z3R1yp8RR69PNNiGxkWjG829ehzEDHy7ueeqNQfeGs", "mimeType": "image/jpeg"}], "creators": ["tz29fAaL3ihzq5uBKAKQMZ9hZifXpGrh9ZVE"], "tags": ["dog", "celebgram", "pembrokewelshcorgi", "corgi", "portait", "blue"], "extra": {}}