{"__version": 1, "token_id": 690909, "symbol": "OBJKT", "name": "Constant Fracture", "description": "Constant Fracture\n\nThe Psychenizer (analog glitch gear) + 2002 Sony DSC-717 (digital film camera)\n\nMore glitched photography to come", "artifact_uri": "ipfs://QmNvz44NkCw2UC3d9b2p5xdt9bzSjB63u4wA5gkaNFBU25", "display_uri": "ipfs://QmXNNgEGeV6VaZc3Rai3hSBCB3XV6uuGsWxygC7qJq9FDf", "thumbnail_uri": "ipfs://QmNrhZHUaEqxhyLfqoq1mtHSipkWHeT31LNHb1QEbDHgnc", "formats": [{"uri": "ipfs://QmNvz44NkCw2UC3d9b2p5xdt9bzSjB63u4wA5gkaNFBU25", "mimeType": "image/jpeg"}], "creators": ["tz1QF2KV63jokHtw82fFzWtPvDVV5QwxzRef"], "tags": ["DownsFilms", "VHS", "Glitch", "Photography", "Sony", "DigitalFilm", "Visualart", "digitalart", "videosynthesis", "glitchart", "analog", "cybershot", "trippy"], "extra": {}}