{"__version": 1, "token_id": 648121, "symbol": "OBJKT", "name": "Faun, The Wanderer (Animated)", "description": "\"Harness this lunar wealth. May it become the Oracle that allows you to peruse the Aether between worlds unknown.\" - Faun", "artifact_uri": "ipfs://QmPRkYc5cHcoaVxhXyHyskECr9bLLbZgkA1acLNunq1vqa", "display_uri": "ipfs://QmcPsQXLrvZ3qjXNvWU3hzBqgWyjoXc5uwdDX7xKokj5Bn", "thumbnail_uri": "ipfs://QmNrhZHUaEqxhyLfqoq1mtHSipkWHeT31LNHb1QEbDHgnc", "formats": [{"uri": "ipfs://QmPRkYc5cHcoaVxhXyHyskECr9bLLbZgkA1acLNunq1vqa", "mimeType": "video/mp4"}], "creators": ["tz1Rk7niQcvsPshBUiAJfWavr7ruEUpMS2P5"], "tags": ["whisper", "lonely", "deity", "blender", "steampunk", "moonkin", "clockwork", "solitude", "nftart", "animated", "sounddesign", "depression", "mythology", "design", "anime", "moon", "entity", "clean", "dark", "video", "japanese", "octane", "drifting", "music", "space", "astrology", "gold", "dreams", "cinema4d", "song", "enko", "lunar", "feminine", "sad", "character", "mechanism", "enkochamber", "love", "technology", "beautiful", "alone", "series", "lucid", "planets", "god", "cinematic", "cosmic", "portrait", "folklore", "movie", "astral", "brother", "stars", "sound", "animation", "lullaby", "floating"], "extra": {}}