{"__version": 1, "token_id": 653562, "symbol": "HEN3", "name": "Here and Now: Edition Three #442", "description": "Here and Now: Edition Three #442\nThe Tower\nCreated by Beets (@wideawakebeets)\nTicket artwork by liasomething | 4000x4000 pixels | September 2021 \nImmersive experience launches 15th October, 2021\nhttps://wideawakeprojects.com/tower/\n\nTRAITS\nThe higher the Rarity Score, the rarer it is. \n\nColor Range: Wide (55.08%)\nShape Is Filled: No (98.33%)\nCentral Color: Green (27.80%)\nShape: Rectangle (56.63%)\nBackground: Black (79.79%)\nStroke: Thinner Lines (97.17%)\n\n(The percentage represents the total # of tickets that share that trait)\n\nRARITY SCORE (RS) = 10.4779\n\nHighest RS: 106.4227\nLowest RS: 10.4779\n\nHERE AND NOW aims to elevate artists, and collectors, collectively. Holding tickets from previous experiences rewards collectors. Beets is committed to creating six editions, imagine if you had all six.\nView the roadmap here: https://wideawakeprojects.com/roadmap/\n\n**If you bought this 1/1 on secondary, please DM @wideawakebeets, so he can register you as a ticketholder**", "artifact_uri": "ipfs://bafybeifxncojkhfrpfhjryqnfenyknuxzqzrqqa2xa7jcf6x6finblzeeq", "display_uri": "ipfs://bafybeihw6ihizwjl7le4gazupvgm4za36xn6rv3gm6i4f7fgh6ll2qraym", "thumbnail_uri": "ipfs://bafybeidilkt7mdwd5q7c3wqloitlqwfsskktpkokvkimpn3anocfuokxuu", "formats": [{"uri": "ipfs://bafybeifxncojkhfrpfhjryqnfenyknuxzqzrqqa2xa7jcf6x6finblzeeq", "mimeType": "image/png", "hash": "32e7c7d777c1cf7753e2ac0966c6f9e8042c9c5da04586b9b6e8fb02bddc2732", "fileSize": 5099330, "dimensions": {"value": "4000x4000", "unit": "px"}}, {"uri": "ipfs://bafybeihw6ihizwjl7le4gazupvgm4za36xn6rv3gm6i4f7fgh6ll2qraym", "mimeType": "image/png", "hash": "b376eff73ad060fd980e38b651746274cfcfb47997ed9babbf845b6d4af1e125", "fileSize": 555166, "dimensions": {"value": "1024x1024", "unit": "px"}}], "creators": ["tz1LxTWreHQ7tYBqGqEN7vPsXnvVKkK96Cg9"], "tags": ["liveexperience", "beets", "hereandnow", "liveevent", "interactive"], "extra": {}}