{"__version": 1, "token_id": 515604, "symbol": "OBJKT", "name": "WickyMonkey #17", "description": "Wicky Monkey #13 is generated NFT avatar Collectible Art.  Only on Tezos Blockchain.\nDont to be late collect 1111 expressions n my style on HEN! ", "artifact_uri": "ipfs://QmTjRZ2j7nfb7fR73ax4ZZs7RJtfWSRqD9wdzUpCf8zxkh", "display_uri": "ipfs://QmbXnpNZLgSd2n2Jv9eRj6qLpouvCYTFicc7J9fJN65FqT", "thumbnail_uri": "ipfs://QmNrhZHUaEqxhyLfqoq1mtHSipkWHeT31LNHb1QEbDHgnc", "formats": [{"uri": "ipfs://QmTjRZ2j7nfb7fR73ax4ZZs7RJtfWSRqD9wdzUpCf8zxkh", "mimeType": "image/png"}], "creators": ["tz1NsiuRoXe44ZjCua6dXCqinSvB1NS7hnqc"], "tags": ["wickymonkey", "hen", "hicetnunc", "objkt", "cleannft", "nftcollector", "nftcollection", "nft", "nftart", "crypto", "cartoon", "collectible", "avatar", "mascot"], "extra": {}}