{"__version": 1, "token_id": 638367, "symbol": "OBJKT", "name": "The Koala's 400 Monument", "description": "Celebrating 400 Followers of my Twitter Account, Thanks to all my friends that always supporting me since i was start my journey into this NFT Universe until nowadays, and also thanks to all participants in this awesome NFT community that always supportive, kind, and helps each other. Much love for y'all.\n\nBest Regards,\nFunkykoala a.k.a kolsky", "artifact_uri": "ipfs://QmdXF1qGHYPrnBmk5gYkJeXpjE1CVCc2YL9qgyBvu5uK9Y", "display_uri": "ipfs://QmdXF1qGHYPrnBmk5gYkJeXpjE1CVCc2YL9qgyBvu5uK9Y", "thumbnail_uri": "ipfs://QmdXF1qGHYPrnBmk5gYkJeXpjE1CVCc2YL9qgyBvu5uK9Y", "formats": [{"uri": "ipfs://QmdXF1qGHYPrnBmk5gYkJeXpjE1CVCc2YL9qgyBvu5uK9Y", "mimeType": "image/gif"}], "creators": ["tz1PiTp8kkCBF1E8sY3zhpuafpmeMn75mKJi"], "tags": ["celebrate", "400", "followers", "twitter", "statue", "monument", "voxel", "voxelart", "indonesia", "cigar", "chainsmoker"], "extra": {}}