{"__version": 1, "token_id": 680923, "symbol": "OBJKT", "name": "22022022 - Once In A Lifetime", "description": "A short visual commentary on the CryptoArt/NFT scene today.\n\nNoisy, brittle, progressive and saturated with hack schemers, scammers & daydreamers.\nNever again will we experience the synchronicity of today as a palindrome and super numerical state. Remember how far we've come and how far we have still to go...", "artifact_uri": "ipfs://QmctVG3Wzw1qvQUV8Ncsy98NxYXUuwALFDua4f8ajZEHwj", "display_uri": "ipfs://QmUzPtnmqHZN2xBU3z5qCCxR9n1fnXece1sujSD4JVExHi", "thumbnail_uri": "ipfs://QmNrhZHUaEqxhyLfqoq1mtHSipkWHeT31LNHb1QEbDHgnc", "formats": [{"uri": "ipfs://QmctVG3Wzw1qvQUV8Ncsy98NxYXUuwALFDua4f8ajZEHwj", "mimeType": "video/mp4"}], "creators": ["tz1hPLHRVbz4s3XKiwGzSCL9VmyLkZUvtFpv"], "tags": ["CryptoArt", "22022022", "NFT", "snapshot", "glitchy", "cyberpunk", "trash", "align", "palindrome"], "extra": {}}