{"__version": 1, "token_id": 695223, "symbol": "OBJKT", "name": "Spirit of A Champion", "description": "Rabb entered the boxing ring with fire-burning enthusiasm. He had to win this match to get the right of residency. The right to get a place to live is important for him and his children and grandchildren in the future.\n\nResolutions: 2304 x 3840\nSize: 3,3MB", "artifact_uri": "ipfs://QmbkxHND26R4nzb2BBf9fzq7KuisEps9pW5rmHA6NQX5Mx", "display_uri": "ipfs://QmW6X8YKKpAwvPqV82CrquSgP5Br4zFY1RZZ8kSJEwvBqE", "thumbnail_uri": "ipfs://QmNrhZHUaEqxhyLfqoq1mtHSipkWHeT31LNHb1QEbDHgnc", "formats": [{"uri": "ipfs://QmbkxHND26R4nzb2BBf9fzq7KuisEps9pW5rmHA6NQX5Mx", "mimeType": "image/png"}], "creators": ["tz1LtRMQbmSzqknEFGwWxmb1MiPW7dAHJKwQ"], "tags": ["nftartist", "Illustrations", "Indonesiaartist", "nftindonesia", "aseannftartist", "rabbs"], "extra": {}}