{"__version": 1, "token_id": 645661, "symbol": "OBJKT", "name": "DWI", "description": "\"DWI\" by Arsalan Aboomohsenpour is now available on hic et Nunc.\n\n\"DWI\" is a 60FPS video made of algorithms and autonomous mathematical processes.\n\nGenerative Art is Art or design generated, composed, or constructed through computer software algorithms or similar mathematical or mechanical autonomous processes. The most common generative art forms are graphics that visually represent complex processes, music, or language-based compositions like poetry. Other applications include architectural design, models for understanding evolution, and artificial intelligence systems.", "artifact_uri": "ipfs://QmdAJrqj6QrDj8Js5GPfEUSLvdnXgihzxfV2ET2v19CTMo", "display_uri": "ipfs://QmTKc8kzaAjyT4yfRNsT5fTN5vNMU1svwBP7B86TtdGmXa", "thumbnail_uri": "ipfs://QmNrhZHUaEqxhyLfqoq1mtHSipkWHeT31LNHb1QEbDHgnc", "formats": [{"uri": "ipfs://QmdAJrqj6QrDj8Js5GPfEUSLvdnXgihzxfV2ET2v19CTMo", "mimeType": "video/mp4"}], "creators": ["tz1aN2dWA2twPGM18hn6hxtXTZAiuBh6Ts8S"], "tags": ["2d", "Abstract", "Color", "purple", "abumohsenpour", "contemporaryart", "abstract", "geometric", "code", "generative", "geometry", "generativeart", "mathematic", "lineart", "art", "noise", "line", "animate", "animation", "Generative", ""], "extra": {}}