{"__version": 1, "token_id": 684363, "symbol": "OBJKT", "name": "\ud835\udd8d\ud835\udd99\ud835\udd92\ud835\udd91_dream07 \ud83c\udf08\ud83d\udca1.GIF", "description": "\"SETUP_FAIL\" (7/16) Part of the \"\ud835\udd8d\ud835\udd99\ud835\udd92\ud835\udd91_dream\" series (2022) 512x512 32 colors (5,2MB)", "artifact_uri": "ipfs://QmTS33GTgT6zpx1M82VoNX9mXU8nJGiY3EKuXEtTxiUVkj", "display_uri": "ipfs://QmTS33GTgT6zpx1M82VoNX9mXU8nJGiY3EKuXEtTxiUVkj", "thumbnail_uri": "ipfs://QmTS33GTgT6zpx1M82VoNX9mXU8nJGiY3EKuXEtTxiUVkj", "formats": [{"uri": "ipfs://QmTS33GTgT6zpx1M82VoNX9mXU8nJGiY3EKuXEtTxiUVkj", "mimeType": "image/gif"}], "creators": ["tz1e2M5Jb8gcv5mB1CDKZLzPtVXrUn4zGDmk"], "tags": ["gif", "glitch", "glitchart", "pixelart", "pixel", "3D", "postinternet", "digital", "vaporwave", "lxtxcx"], "extra": {}}