{"__version": 1, "token_id": 661543, "symbol": "OBJKT", "name": "Serenadium", "description": "Enter the Serenadium\u2019s death battles at your own risk. In all of history, this has endured as one of the most treacherous competitions. Those who fail to win their match get a one-way ticket to the crocodile pit. But you know what they say - high risk, high reward.", "artifact_uri": "ipfs://QmT9UqjxoctZ6FyR6f2xxSDkLKCvqeEMqUR8ccjwKsEL76", "display_uri": "ipfs://QmbNoBkX9zuk522MC8qRgCo6jzmoJq3RLHiwsnsAi61t4q", "thumbnail_uri": "ipfs://QmNrhZHUaEqxhyLfqoq1mtHSipkWHeT31LNHb1QEbDHgnc", "formats": [{"uri": "ipfs://QmT9UqjxoctZ6FyR6f2xxSDkLKCvqeEMqUR8ccjwKsEL76", "mimeType": "image/jpeg"}], "creators": ["tz2Gu5ouBQ1FkrawjFuLBY8XHn2wTHVo9DM9"], "tags": ["illustration", "digitalart", "posterart", "retro", "vintagepop", "typography"], "extra": {}}