{"__version": 1, "token_id": 686343, "symbol": "OBJKT", "name": "The Thin White Duke", "description": "From The Words of Idols collection. Images rendered with VQGAN+CLIP using David Bowie song lyrics as text prompts. Post render editing completed in PS. By @dehiscenceart, 2021. Minted February 28, 2022.", "artifact_uri": "ipfs://QmQ365uX1JYUDUT2N7ydjRy43vhDuhpUKiuYevhV3uBcHw", "display_uri": "ipfs://QmcFtNLgpo3QKYtikwmeawT53XqytvzZrckVt3oYydwa7R", "thumbnail_uri": "ipfs://QmcSiyiNhjkq3bxKft45RGt2auTZhAiV3fBhRAg1WvZX31", "formats": [{"uri": "ipfs://QmQ365uX1JYUDUT2N7ydjRy43vhDuhpUKiuYevhV3uBcHw", "mimeType": "image/jpeg"}], "creators": ["tz1TtZmtxhiWc8Nv6AtC1YjVCtJoFjv4nTqL"], "tags": ["aiart", "gan", "darkart", "davidbowie", "surreal", "vqganclip", "dehiscence"], "extra": {}}