{"__version": 1, "token_id": 388896, "symbol": "OBJKT", "name": "WARHOLIC #2", "description": "'WARHOLIC #2' by TenFiveEleven 2021 \nVARIANT #2 (1/10) \n\nOriginal Piece 2021 (PAINT, Digital, Collage, Digital Paint)  \nOriginal Digital Paint / Canvas 2021 \n\nWARHOLIC #2 - (1/10) - **NOT A WARHOL", "artifact_uri": "ipfs://QmdCnje9iakJSc5H4vPgeidbCoDiLhh8eQZxrRpDA6iQpp", "display_uri": "ipfs://QmZEpuXi9PEY375V9uLYoMhDvC1wHKZpJ6vW6bT45LysSz", "thumbnail_uri": "ipfs://QmNrhZHUaEqxhyLfqoq1mtHSipkWHeT31LNHb1QEbDHgnc", "formats": [{"uri": "ipfs://QmdCnje9iakJSc5H4vPgeidbCoDiLhh8eQZxrRpDA6iQpp", "mimeType": "image/jpeg"}], "creators": ["tz1cjLwdFdXCA8Sxi9SYqmq1mmsas7Zc4wEn"], "tags": ["pop", "art", "popart", "fineart", "trashart", "trash", "digital", "collage", "painting", "homage", "jpeg", "nostalgia", "ironic", "remix"], "extra": {}}