{"__version": 1, "token_id": 692196, "symbol": "OBJKT", "name": "Absurtz Face #144", "description": "In 3050, 222 Absurtz Face invades the Earth to choose some Earthican to become a host for their bodies and grant unique powers. Those Earthican can transmit the powers to the next generation, or keep it to themselves and be immortal. \n\n1/1 Generative-Collectibles of Absurtzian army, on #Tezos blockchain\n\nAttributes\nEyes: Wiggly\nHead: Fran\nShirt: Marble\nBody: Miner\nAccessories: Horn\nBackground: Living Coral", "artifact_uri": "ipfs://QmbPKcf3omVGTtZM6fY1yDm94pCQWeTPRYcxBqKWdatYAK", "display_uri": "ipfs://QmWzCshWcq9eXARV4LwLr99c2W41YM1ZX6GnEMPXNdUvxP", "thumbnail_uri": "ipfs://QmNrhZHUaEqxhyLfqoq1mtHSipkWHeT31LNHb1QEbDHgnc", "formats": [{"uri": "ipfs://QmbPKcf3omVGTtZM6fY1yDm94pCQWeTPRYcxBqKWdatYAK", "mimeType": "image/jpeg"}], "creators": ["tz1fAi845nBNUbEjp4zrhS9PxyAox2a57QHP"], "tags": [""], "extra": {}}