{"__version": 1, "token_id": 638420, "symbol": "OBJKT", "name": "Autumn at Cima D'Ometto", "description": "Monte Bo as seen from Cima D'Ometto (1911m above s.l.), Valsesia (Piedmont, IT).\nWonderful hike (especially in autumn) from Scopello to Alpe di Mera and then to Cima D'Ometto.\n\nAutumn 2020.\n\n6000x4000 px", "artifact_uri": "ipfs://QmcKutTpS93B7MeCMcgEsHrm7XavzhKbTkNXgtpdh5qz4C", "display_uri": "ipfs://QmPzUUFHpdUJXsgnFwujr8tTfamgkWHrPvhQAEqBH8P9Ey", "thumbnail_uri": "ipfs://QmNrhZHUaEqxhyLfqoq1mtHSipkWHeT31LNHb1QEbDHgnc", "formats": [{"uri": "ipfs://QmcKutTpS93B7MeCMcgEsHrm7XavzhKbTkNXgtpdh5qz4C", "mimeType": "image/jpeg"}], "creators": ["tz1hqbmviAvW3Xv3m46vxVNChqmHMYQU641i"], "tags": ["photography", "landscape", "landscapephotography", "mountains", "valsesia", "autumn", "italy"], "extra": {}}