{"__version": 1, "token_id": 655878, "symbol": "OBJKT", "name": "doodles from class ", "description": "'what a fool'\n\n--\n8 Exclusive Airdrops.\n--\n\nFollow my Twitter @killjoyartclub for news on all 3D printed Companions for the Choir Club collection.", "artifact_uri": "ipfs://QmWxEicdvAbN4B9zPZ7dPP6V9e8K4sJuynmg4ZShKTHw98", "display_uri": "ipfs://QmPa9pzRvGs6SWF8S2C1qMLP3Sk4YhyUShAs9yR6Ld115Z", "thumbnail_uri": "ipfs://QmNrhZHUaEqxhyLfqoq1mtHSipkWHeT31LNHb1QEbDHgnc", "formats": [{"uri": "ipfs://QmWxEicdvAbN4B9zPZ7dPP6V9e8K4sJuynmg4ZShKTHw98", "mimeType": "image/png"}], "creators": ["tz1QtcA4MvmCSLJ7DdvHzXEq2sm2bEC37xdG"], "tags": ["doodles", "choirclub", "digital", "airdrop", "illustrator", "png", "gif", "glb", "blender", "handtohen", ""], "extra": {}}