{"__version": 1, "token_id": 692244, "symbol": "OBJKT", "name": "Jaran Kepang", "description": "Jaran Kepang is a dance art that is played with the property in the form of an imitation horse, which is made of woven bamboo It is said that the Jaran Kepang dance is a trance dance. There is also a version that says that the Jaran Kepang dance depicts the story of a beautiful youth troop with the title Jathil riding a white horse. Regardless of its origin and historical value, Jaran Kepang reflects the spirit of heroism and the military aspect of a cavalry or cavalry troop. This can be seen from the rhythmic, dynamic, and aggressive movements, through the waving of woven bamboo, imitating the movements of a horse in the midst of war.\n\n2500 X 3000 PX\n600 Dpi", "artifact_uri": "ipfs://QmU4zSBqD7trWNHWoVCL51htRA7oXj49ecqsDVtTGw79Eo", "display_uri": "ipfs://QmXqZvZdxwGswNnj8WPJVfBkBwwv5Ki5MZeuujcb5ncbnN", "thumbnail_uri": "ipfs://QmNrhZHUaEqxhyLfqoq1mtHSipkWHeT31LNHb1QEbDHgnc", "formats": [{"uri": "ipfs://QmU4zSBqD7trWNHWoVCL51htRA7oXj49ecqsDVtTGw79Eo", "mimeType": "image/jpeg"}], "creators": ["tz1NZQVM6pwPYRgVqcrdAmTdpx2Pwxv7Ms81"], "tags": ["Dance", "art", "psycedelic", "illustration", "horse", "ardhdwp"], "extra": {}}