{"__version": 1, "token_id": 700005, "symbol": "OBJKT", "name": "\u30b5\u30a4\u30d0\u30fc\u30c9\u30e9\u30b4\u30f3 /// CYBRDRAGO", "description": "8.0 Mechaverse Cyber Dragon\n// 4500 x 3500 px | 300 dpi | personal use only.\nAngoes25 CreativeSupply Station | GRPHCSHMN | Agus Setyawan\n\u00a92022.SRG.IDN | MMXXII.", "artifact_uri": "ipfs://QmWJ6YUAx4zTsidCPjuQJQMFGUhkhCzumcoKY9jtLDZrAt", "display_uri": "ipfs://QmX6z9JfRuVLqQAXbY7EyrTe1r7Jx5UxhLjr7LYrBLMkkc", "thumbnail_uri": "ipfs://QmcGxXpasSVX8fKanQyigbetnRUTeMHvjdPKbukb8BP4SV", "formats": [{"uri": "ipfs://QmWJ6YUAx4zTsidCPjuQJQMFGUhkhCzumcoKY9jtLDZrAt", "mimeType": "image/png"}], "creators": ["tz1WcEHgjivUndAq5H91gwnjLYTnvD4M45Fj"], "tags": ["mecha", "mechaverse", "dragon", "naga", "hen700k", "cyber", "cyberverse", "illustration", "art", "fire", "robot", "futuristic", "scifi", "myth", "japanese"], "extra": {}}