{"__version": 1, "token_id": 650822, "symbol": "OBJKT", "name": "Mors 'Lamafa & Saguni'", "description": "L.-../A.-/M--/A.-/F..-./A.-\nS.../A.-/G--./U..-/N-./I.. \n-\n-\nMelompat, menikam lewat jari tergenggam\nLamafa tangguh bertenaga penuh\nPerahu terangkat, dan terbalik, dan terhantam\nSisa satu, 7 tenggelam.\n\nMatahari mengambang di permukaan, \nmelerai Lamafa dan Saguni yg berhadapan\ndi kedalaman Lamalera.\n\n*****\nLamafa (Juru Tikam Paus)\nSaguni (Paus Pembunuh)\n\n____________________________\n\nThe tough Lamafa was full force\nLeapt, stabbed, with fingers held\nThe boat was hit, and lifted, and flipped\nOne Lamafa remaining, 7 drowned.\n\nThe sunset floats on the surface, \ninterfering Lamafa and Saguni \nwho face each other in the depth of Lamalera.\n\n*****\nLamafa (Whale Hunter)\nSaguni (Killer Whale)\n\n----\n\nI hope that is correct translation,\ninspired from my old prose (Nov 2013, Tumblr era)\n-\nThis is my token of gratitude. \nBig thank you for Mors fellow creators & collectors for your continued support along my few months journey on the NFT space.\n\n", "artifact_uri": "ipfs://QmU9hjk6qz5ErkCqMUvq8ypxL14GYnL5m521CFaxHAXKS9", "display_uri": "ipfs://QmU9hjk6qz5ErkCqMUvq8ypxL14GYnL5m521CFaxHAXKS9", "thumbnail_uri": "ipfs://QmNrhZHUaEqxhyLfqoq1mtHSipkWHeT31LNHb1QEbDHgnc", "formats": [{"uri": "ipfs://QmU9hjk6qz5ErkCqMUvq8ypxL14GYnL5m521CFaxHAXKS9", "mimeType": "image/gif"}], "creators": ["tz1PjuxgrSq8okSYbEBD8VRU6wEePUN9vsLf"], "tags": ["Mors", "sandimors", "GIF", "MorsLamafaSaguni", "morsecode", "code", "whale", "hunter", "gratitude"], "extra": {}}