{"__version": 1, "token_id": 699222, "symbol": "OBJKT", "name": "Other Side", "description": "the other side of social media is sacrificing self-respect for popularity and wealth\n\nThis image was created using pointillism on a 29.7 x 42.0 cm worksheet with a resolution of 300 pixels/inch", "artifact_uri": "ipfs://Qmax5yxujcnwTVw8tGWUXBaSP7GGoWmWaPkJhkFCWpyrPf", "display_uri": "ipfs://QmQdXCmpAqMjYTBz2zneMuRpFdxuLCeW6Cwv3WQ1azV23H", "thumbnail_uri": "ipfs://QmNrhZHUaEqxhyLfqoq1mtHSipkWHeT31LNHb1QEbDHgnc", "formats": [{"uri": "ipfs://Qmax5yxujcnwTVw8tGWUXBaSP7GGoWmWaPkJhkFCWpyrPf", "mimeType": "image/jpeg"}], "creators": ["tz2MQyNQbVcnvQuJjVa9uuKDEasGLqRgWv9d"], "tags": ["art", "artwork", "pointillism", "drawing", "nft", "woman", "digitalpainting"], "extra": {}}