{"__version": 1, "token_id": 642845, "symbol": "OBJKT", "name": "RegularPumpkins #446", "description": "Regular Pumpkins is 3030 Generative Collectible item.This pumpkin is not only present at the halloween event, but will accompany your \nday and now we are on tezos blockchain", "artifact_uri": "ipfs://QmbLtAh2RQFsXUqp1ivAdLyzhZn2L8KppcanR6BTBbu3gs", "display_uri": "ipfs://QmU6Co9C2oLqNhYZZozY2JZpfn5bXXfPLkGi6V2R8NCEEp", "thumbnail_uri": "ipfs://QmW5HYjt2XNdUxnqGXo8VdERrUykiDiL3D8XogbCt4ockr", "formats": [{"uri": "ipfs://QmbLtAh2RQFsXUqp1ivAdLyzhZn2L8KppcanR6BTBbu3gs", "mimeType": "image/jpeg"}], "creators": ["tz1McVCEySakqp3uwJnmh8dZ4PLttrapxasU"], "tags": ["RegularPumpkins", "Pumpkin", "NFTart", "Collectible", "Generative", "PFP", "Avatar", "PFPNFT"], "extra": {}}