{"__version": 1, "token_id": 657241, "symbol": "OBJKT", "name": "Battal Ebr\u00fb / Marbling Art #9", "description": "Limited Edition of 20. \nDate created 18 Jan 2022 - High Res image (2678\u200a\u00d7\u200a3957 pixels)\nUnique piece of hand-made, non-digital marbling art (Ebr\u00fb/Turkish Paper).\nCreated by Ertugrul Incel with traditional Ebr\u00fb method, using earth dyes and water-based solution, and transferred on chamois paper.", "artifact_uri": "ipfs://QmdweAYtJG5orfQFJSgKFzzLktffekqJ7ziiycz5aC36zt", "display_uri": "ipfs://QmSThUN2drpJC1U6H4SHGgjMt9GjUNDmQ1ZdvyMMhYDxDp", "thumbnail_uri": "ipfs://QmNrhZHUaEqxhyLfqoq1mtHSipkWHeT31LNHb1QEbDHgnc", "formats": [{"uri": "ipfs://QmdweAYtJG5orfQFJSgKFzzLktffekqJ7ziiycz5aC36zt", "mimeType": "image/jpeg"}], "creators": ["tz1ZGYVNyJz4m3iG99KBRL7Azp81EAdR3u9V"], "tags": ["nondigital", "marblingart", "dye", "ertugrulincel", "microcosmos", "onpaper", "handmade", "abstract", "ebru"], "extra": {}}