{"__version": 1, "token_id": 694528, "symbol": "OBJKT", "name": "Sunflowers", "description": "Sunflowers, stabbed.\nSymbolism is a candid curtain over the unbearable truth.\n\n\nGenerative drawing\nMade with Javascript code\nFormat JPG\nResolution 5960\u200a\u00d7\u200a8400\n\n\n#peace4Ukraine\nFundraising for Ukraine people : 90% of primary sale / 10% of secondary sale", "artifact_uri": "ipfs://QmXfFUDyroBXswgNg2rpHMvPBCmbUTxxNSqAihTCaYNEcv", "display_uri": "ipfs://QmaNdzLakJaeAJ4JKCHDJtUtcPSXdEtKR5XUPRFks16TRk", "thumbnail_uri": "ipfs://QmNrhZHUaEqxhyLfqoq1mtHSipkWHeT31LNHb1QEbDHgnc", "formats": [{"uri": "ipfs://QmXfFUDyroBXswgNg2rpHMvPBCmbUTxxNSqAihTCaYNEcv", "mimeType": "image/jpeg"}], "creators": ["tz1a6ho9fLuyDPUvx48vV5NGF66wfW18LQZb"], "tags": ["zancan"], "extra": {}}