{"__version": 1, "token_id": 685171, "symbol": "OBJKT", "name": "Flower Girl", "description": "A girl who has full power over flowers, a girl who is blessed, and of course her beautiful face is like an angel.\n\nThis is artwork from my imagination, but I really fell in love with it", "artifact_uri": "ipfs://QmSjmEN6UQAB7YfrhNSsrexcm9SkZEHNDmX5Upsk3YGrqh", "display_uri": "ipfs://QmP1G65wNcF1izngLtZ9aVW5amKu9cnDg8jyQtLrLcHYcn", "thumbnail_uri": "ipfs://QmWsM21Cnr9GuFJSimpxnf45G7TEeRFWJ4nHNqkM2B5b5n", "formats": [{"uri": "ipfs://QmSjmEN6UQAB7YfrhNSsrexcm9SkZEHNDmX5Upsk3YGrqh", "mimeType": "image/jpeg"}], "creators": ["tz1ZZx2R6ziyJ1L8oS9vNUHXLRUo1yqNPV39"], "tags": ["doodle", "character", "art", "colorful", "cartoon", "animation", "rainbow", "digitalart", "drawing", "handdraw", "flowers", "anime", "animegirl"], "extra": {}}