{"__version": 1, "token_id": 646119, "symbol": "OBJKT", "name": "Reality Photo #1 - \"Void Gateaway\"", "description": "A light soaring above your head but is it a light? or it is something that lurking on your flesh? are they to consume you or you to consume them? you are one with void in everywhere you go, you will be attached by it and it will try to invite you to gain its power? or them to gain you so you can accompany them?", "artifact_uri": "ipfs://QmSGDHX3JBeZKyvetkdJ7JgZkyi7JEm85rixxX2rZLwvse", "display_uri": "ipfs://QmSGDHX3JBeZKyvetkdJ7JgZkyi7JEm85rixxX2rZLwvse", "thumbnail_uri": "ipfs://QmNrhZHUaEqxhyLfqoq1mtHSipkWHeT31LNHb1QEbDHgnc", "formats": [{"uri": "ipfs://QmSGDHX3JBeZKyvetkdJ7JgZkyi7JEm85rixxX2rZLwvse", "mimeType": "image/gif"}], "creators": ["tz1f4D1FyD3b2GSKbhNd4T6zMYKMjt8V7M8P"], "tags": ["void", "photography", "ghost", "photo", "gif", "fluorescentlights", "horror", "surrealism"], "extra": {}}