{"__version": 1, "token_id": 688787, "symbol": "OBJKT", "name": "Whatever People Say I Am, That's What I'm Not", "description": "Whatever People Say I Am, That's What I'm Not is the debut studio album by English rock band Arctic Monkeys, released on 23 January 2006 by Domino Recording Company and on 21 February 2006 in the United States. The album includes their first two singles \"I Bet You Look Good on the Dancefloor\" and \"When the Sun Goes Down\", as well as re-recorded versions of both tracks from the band's debut EP, Five Minutes with Arctic Monkeys.", "artifact_uri": "ipfs://QmbD2N15vpSEAm6cvoBQp2UaJwXTP8fjUe7djimjkwNeaQ", "display_uri": "ipfs://QmUheHhfBtaCowVdseNWG4iAyY3ZVW2BKwYd5aDKdV2iYQ", "thumbnail_uri": "ipfs://QmNrhZHUaEqxhyLfqoq1mtHSipkWHeT31LNHb1QEbDHgnc", "formats": [{"uri": "ipfs://QmbD2N15vpSEAm6cvoBQp2UaJwXTP8fjUe7djimjkwNeaQ", "mimeType": "image/jpeg"}], "creators": ["tz1i9Jbej7sM2TvtpZ9YrJr8wUtpZ91BQ6vf"], "tags": ["digitalart", "pixelart", "8bit", "arcticmonkeys", "album", "cover", "british"], "extra": {}}