{"__version": 1, "token_id": 643751, "symbol": "OBJKT", "name": "Forgotten Persona #4", "description": "Animated GIF | 6 fps| 2048 x 2048 | RGB | sRGB IEC61966-2.1\n\nWhen I start drawing, I don't know yet what it will be. With each frame that I draw, the sketch is formed, step by step, into a figure. A person from my imagination, or maybe even a memory. A deceased person.\nThe light around, seeks the accents, which I need to perceive this forgotten someone.", "artifact_uri": "ipfs://QmaQYFVMmeM3bFNBKU3SxCbv2TNm2vUi6HJBg5rqxaiwRD", "display_uri": "ipfs://QmaQYFVMmeM3bFNBKU3SxCbv2TNm2vUi6HJBg5rqxaiwRD", "thumbnail_uri": "ipfs://QmNrhZHUaEqxhyLfqoq1mtHSipkWHeT31LNHb1QEbDHgnc", "formats": [{"uri": "ipfs://QmaQYFVMmeM3bFNBKU3SxCbv2TNm2vUi6HJBg5rqxaiwRD", "mimeType": "image/gif"}], "creators": ["tz1fVaM75n4UCmrTpDWMvVUR1EnpUoBjX6vW"], "tags": ["portrait", "gif", "animated", "soul", "light", "memory", "handmade", "digitalart"], "extra": {}}